n64tex/__init__.py
n64tex/formats/__init__.py
n64tex/formats/base.py
n64tex/formats/ci4.py
n64tex/formats/ci8.py
n64tex/formats/i4.py
n64tex/formats/i4a.py
n64tex/formats/i8.py
n64tex/formats/i8a.py
n64tex/formats/rgba.py
n64tex/formats/rgba5551.py
n64tex-1.0.1.dist-info/LICENSE
n64tex-1.0.1.dist-info/METADATA
n64tex-1.0.1.dist-info/WHEEL
n64tex-1.0.1.dist-info/entry_points.txt
n64tex-1.0.1.dist-info/top_level.txt
n64tex-1.0.1.dist-info/RECORD
