Metadata-Version: 2.1
Name: n64tex
Version: 1.0.1
License: GNU GENERAL PUBLIC LICENSE
Requires-Python: >=3.10
License-File: LICENSE
Requires-Dist: numpy
Requires-Dist: Pillow
